swarm_pretalx/__init__.py
swarm_pretalx/apps.py
swarm_pretalx/locale/de_DE/LC_MESSAGES/.gitkeep
swarm_pretalx/locale/fr_FR/LC_MESSAGES/.gitkeep
swarm_pretalx/signals.py
swarm_pretalx/static/swarm_pretalx/.gitkeep
swarm_pretalx/tasks.py
swarm_pretalx/templates/swarm_pretalx/.gitkeep
swarm_pretalx-0.1.5.dist-info/LICENSE
swarm_pretalx-0.1.5.dist-info/WHEEL
swarm_pretalx-0.1.5.dist-info/METADATA
swarm_pretalx-0.1.5.dist-info/RECORD
